LICENSE.md
MANIFEST.in
README.rst
pyproject.toml
requirements.core.txt
setup.py
core_explore_common_app/__init__.py
core_explore_common_app/admin.py
core_explore_common_app/apps.py
core_explore_common_app/constants.py
core_explore_common_app/discover.py
core_explore_common_app/settings.py
core_explore_common_app/tasks.py
core_explore_common_app/urls.py
core_explore_common_app.egg-info/PKG-INFO
core_explore_common_app.egg-info/SOURCES.txt
core_explore_common_app.egg-info/dependency_links.txt
core_explore_common_app.egg-info/requires.txt
core_explore_common_app.egg-info/top_level.txt
core_explore_common_app/access_control/__init__.py
core_explore_common_app/access_control/api.py
core_explore_common_app/commons/__init__.py
core_explore_common_app/commons/exceptions.py
core_explore_common_app/components/__init__.py
core_explore_common_app/components/abstract_persistent_query/__init__.py
core_explore_common_app/components/abstract_persistent_query/api.py
core_explore_common_app/components/abstract_persistent_query/models.py
core_explore_common_app/components/abstract_query/__init__.py
core_explore_common_app/components/abstract_query/models.py
core_explore_common_app/components/query/__init__.py
core_explore_common_app/components/query/admin_site.py
core_explore_common_app/components/query/api.py
core_explore_common_app/components/query/models.py
core_explore_common_app/components/result/__init__.py
core_explore_common_app/components/result/models.py
core_explore_common_app/migrations/0001_initial.py
core_explore_common_app/migrations/0002_result_blob_url.py
core_explore_common_app/migrations/0003_rename_xml_content_result_content.py
core_explore_common_app/migrations/__init__.py
core_explore_common_app/rest/__init__.py
core_explore_common_app/rest/urls.py
core_explore_common_app/rest/query/__init__.py
core_explore_common_app/rest/query/views.py
core_explore_common_app/rest/result/__init__.py
core_explore_common_app/rest/result/serializers.py
core_explore_common_app/rest/result/views.py
core_explore_common_app/static/core_explore_common_app/common/js/tools.js
core_explore_common_app/static/core_explore_common_app/user/css/query_result.css
