Metadata-Version: 2.1
Name: core-explore-common-app
Version: 2.19.0
Summary: Base exploration function for the curator core project
Home-page: https://github.com/usnistgov/core_explore_common_app
Author: NIST IT Lab
Author-email: itl_inquiries@nist.gov
License-File: LICENSE.md
